MANIFEST.in
README.MD
setup.py
uwsgi_exporter.py
uwsgi_exporter.egg-info/PKG-INFO
uwsgi_exporter.egg-info/SOURCES.txt
uwsgi_exporter.egg-info/dependency_links.txt
uwsgi_exporter.egg-info/requires.txt
uwsgi_exporter.egg-info/top_level.txt