Metadata-Version: 1.1
Name: uwsgi-exporter
Version: 0.1.3
Summary: Prometheus uwsgi stats exporter
Home-page: https://bitbucket.org/semanticapps/uwsgi_exporter/
Author: Shevchenko Vitaliy
Author-email: vetal4444@gmail.com
License: UNKNOWN
Keywords: uwsgi export stats prometheus
Platform: UNKNOWN
Classifier: Programming Language :: Python :: 3.3
Classifier: Programming Language :: Python :: 3.4
Classifier: Programming Language :: Python :: 3.5
